factorio/__init__.py
factorio/factories.py
factorio/fields.py
factorio/lib/__init__.py
factorio/lib/enums.py
factorio/lib/exceptions.py
factorio/py.typed
factorio-0.6.1.dist-info/LICENSE.md
factorio-0.6.1.dist-info/METADATA
factorio-0.6.1.dist-info/WHEEL
factorio-0.6.1.dist-info/RECORD
