Metadata-Version: 2.3
Name: factorio
Version: 0.6.1
Summary: A fixtures replacement tool
Home-page: https://factorio.readthedocs.io/en/stable/
License: BSD-3-Clause
Keywords: tests
Author: Stephanos Kuma
Author-email: "Stephanos Kuma" <stephanos@kuma.ai>
Requires-Python: >=3.9
Classifier: Development Status :: 4 - Beta
Classifier: Intended Audience :: Developers
Classifier: License :: OSI Approved :: BSD License
Classifier: Operating System :: OS Independent
Classifier: Programming Language :: Python :: 3 :: Only
Classifier: Topic :: Software Development :: Build Tools
Requires-Dist: faker (>=30.8)
Requires-Dist: pyutilkit (>=0.6)
Requires-Dist: tzdata ; os_name == 'nt'
Project-URL: Documentation, https://factorio.readthedocs.io/en/stable/
Project-URL: Repository, https://github.com/spapanik/factorio
